asian_bart/__init__.py
asian_bart/modeling_asian_bart.py
asian_bart/tokenization_asian_bart.py
tests/__init__.py
tests/num_params.py
tests/test_ecjk.py
tests/test_ko.py
asian_bart-1.0.2.dist-info/METADATA
asian_bart-1.0.2.dist-info/WHEEL
asian_bart-1.0.2.dist-info/top_level.txt
asian_bart-1.0.2.dist-info/RECORD
