Metadata-Version: 2.1
Name: asian-bart
Version: 1.0.2
Summary: Asian language bart models (En, Ja, Ko, Zh, ECJK)
Home-page: https://github.com/hyunwoongko/asian-bart
Author: Hyunwoong Ko
Author-email: gusdnd852@naver.com
License: UNKNOWN
Platform: UNKNOWN
Classifier: Programming Language :: Python :: 3
Classifier: Programming Language :: Python :: 3.2
Classifier: Programming Language :: Python :: 3.3
Classifier: Programming Language :: Python :: 3.4
Classifier: Programming Language :: Python :: 3.5
Classifier: Programming Language :: Python :: 3.6
Classifier: Programming Language :: Python :: 3.7
Classifier: Programming Language :: Python :: 3.8
Classifier: Programming Language :: Python :: 3.9
Classifier: Topic :: Scientific/Engineering :: Artificial Intelligence
Classifier: Topic :: Software Development :: Libraries
Requires-Python: >=3
Requires-Dist: transformers (>=4)
Requires-Dist: torch
Requires-Dist: sentencepiece
